llama_index/multi_modal_llms/replicate/__init__.py
llama_index/multi_modal_llms/replicate/base.py
llama_index_multi_modal_llms_replicate-0.4.1.dist-info/METADATA
llama_index_multi_modal_llms_replicate-0.4.1.dist-info/WHEEL
llama_index_multi_modal_llms_replicate-0.4.1.dist-info/licenses/LICENSE
llama_index_multi_modal_llms_replicate-0.4.1.dist-info/RECORD
